README.md
setup.py
MiRouter.egg-info/PKG-INFO
MiRouter.egg-info/SOURCES.txt
MiRouter.egg-info/dependency_links.txt
MiRouter.egg-info/requires.txt
MiRouter.egg-info/top_level.txt
mi_router/__init__.py
mi_router/mi_router.py
tests/test.py